azure_data_factory_testing_framework/__init__.py
azure_data_factory_testing_framework/exceptions/activity_not_found_error.py
azure_data_factory_testing_framework/exceptions/dataset_parameter_not_found_error.py
azure_data_factory_testing_framework/exceptions/expression_parameter_not_found_error.py
azure_data_factory_testing_framework/exceptions/function_call_invalid_arguments_count_error.py
azure_data_factory_testing_framework/exceptions/linked_service_parameter_not_found_error.py
azure_data_factory_testing_framework/exceptions/pipeline_activities_circular_dependency_error.py
azure_data_factory_testing_framework/exceptions/pipeline_not_found_error.py
azure_data_factory_testing_framework/exceptions/state_iteration_item_not_set_error.py
azure_data_factory_testing_framework/exceptions/unsupported_function_error.py
azure_data_factory_testing_framework/exceptions/variable_being_evaluated_does_not_exist_error.py
azure_data_factory_testing_framework/exceptions/variable_does_not_exist_error.py
azure_data_factory_testing_framework/exceptions/variable_not_found_error.py
azure_data_factory_testing_framework/functions/__init__.py
azure_data_factory_testing_framework/functions/_expression_activity.py
azure_data_factory_testing_framework/functions/_expression_dataset.py
azure_data_factory_testing_framework/functions/_expression_iteration_item.py
azure_data_factory_testing_framework/functions/_expression_linked_service.py
azure_data_factory_testing_framework/functions/_expression_parameter.py
azure_data_factory_testing_framework/functions/_expression_variable.py
azure_data_factory_testing_framework/functions/_string_utils.py
azure_data_factory_testing_framework/functions/function_argument.py
azure_data_factory_testing_framework/functions/function_call.py
azure_data_factory_testing_framework/functions/function_parser.py
azure_data_factory_testing_framework/functions/functions_repository.py
azure_data_factory_testing_framework/generated/__init__.py
azure_data_factory_testing_framework-0.1.2.dist-info/METADATA
azure_data_factory_testing_framework-0.1.2.dist-info/WHEEL
azure_data_factory_testing_framework-0.1.2.dist-info/RECORD
